[
  {
    "id": 1,
    "src": "https://placehold.co/600x400",
    "alt": "Image 1"
  },
  {
    "id": 2,
    "src": "https://placehold.co/600x400",
    "alt": "Image 2"
  },
  {
    "id": 3,
    "src": "https://placehold.co/600x400",
    "alt": "Image 3"
  },
  {
    "id": 4,
    "src": "https://placehold.co/600x400",
    "alt": "Image 4"
  },
  {
    "id": 5,
    "src": "https://placehold.co/600x400",
    "alt": "Image 5"
  },
  {
    "id": 6,
    "src": "https://placehold.co/600x400",
    "alt": "Image 6"
  },
  {
    "id": 7,
    "src": "https://placehold.co/600x400",
    "alt": "Image 6"
  },
  {
    "id": 8,
    "src": "https://placehold.co/600x400",
    "alt": "Image 6"
  },
  {
    "id": 9,
    "src": "https://placehold.co/600x400",
    "alt": "Image 6"
  },
  {
    "id": 10,
    "src": "https://placehold.co/600x400",
    "alt": "Image 6"
  }
]
